nicelog/__init__.py
nicelog/utils.py
nicelog/colorers/__init__.py
nicelog/colorers/base.py
nicelog/colorers/terminal.py
nicelog/formatters/__init__.py
nicelog/styles/__init__.py
nicelog/styles/base.py
nicelog-0.2.1.dist-info/DESCRIPTION.rst
nicelog-0.2.1.dist-info/METADATA
nicelog-0.2.1.dist-info/RECORD
nicelog-0.2.1.dist-info/WHEEL
nicelog-0.2.1.dist-info/metadata.json
nicelog-0.2.1.dist-info/top_level.txt
