Metadata-Version: 1.1
Name: nicelog
Version: 0.2.1
Summary: Nice colorful formatters for Python logging.
Home-page: http://github.com/rshk/nicelog
Author: Samuele Santi
Author-email: samuele@samuelesanti.com
License: BSD
Platform: UNKNOWN
Classifier: License :: OSI Approved :: BSD License
Classifier: Development Status :: 5 - Production/Stable
Classifier: Programming Language :: Python :: 2.6
Classifier: Programming Language :: Python :: 2.7
